insolver/__init__.py
insolver/configs/__init__.py
insolver/configs/settings.py
insolver/discretization/__init__.py
insolver/discretization/discretizer.py
insolver/discretization/discretizer_utils.py
insolver/feature_engineering/__init__.py
insolver/feature_engineering/dimensionality_reduction.py
insolver/feature_engineering/feature_engineering.py
insolver/feature_engineering/feature_selection.py
insolver/feature_engineering/normalization.py
insolver/feature_engineering/sampling.py
insolver/feature_engineering/smoothing.py
insolver/feature_monitoring/__init__.py
insolver/feature_monitoring/chi2_homogeneity_test.py
insolver/feature_monitoring/homogeneity_report.py
insolver/feature_monitoring/homogeneity_tests.py
insolver/feature_monitoring/psi_homogeneity_test.py
insolver/feature_monitoring/report_template.html
insolver/frame/__init__.py
insolver/frame/frame.py
insolver/interpretation/__init__.py
insolver/interpretation/base.py
insolver/interpretation/dice.py
insolver/interpretation/lime.py
insolver/interpretation/plots.py
insolver/interpretation/shap.py
insolver/model_tools/__init__.py
insolver/model_tools/datasets.py
insolver/model_tools/metrics.py
insolver/model_tools/model_comparison.py
insolver/model_tools/model_utils.py
insolver/pricing/__init__.py
insolver/pricing/evaluation.py
insolver/pricing/generation.py
insolver/pricing/optimization.py
insolver/pricing/pricing.py
insolver/report/__init__.py
insolver/report/comparison_presets.py
insolver/report/error_handler.py
insolver/report/metrics.py
insolver/report/presets.py
insolver/report/report.py
insolver/report/report_template/assets/dist/css/bootstrap.min.css
insolver/report/report_template/assets/dist/css/bootstrap.min.css.map
insolver/report/report_template/assets/dist/css/bootstrap.rtl.min.css
insolver/report/report_template/assets/dist/css/bootstrap.rtl.min.css.map
insolver/report/report_template/assets/dist/js/bootstrap.bundle.min.js
insolver-0.4.29.dist-info/LICENSE
insolver-0.4.29.dist-info/METADATA
insolver-0.4.29.dist-info/WHEEL
insolver-0.4.29.dist-info/entry_points.txt
insolver-0.4.29.dist-info/RECORD
