Metadata-Version: 2.1
Name: insolver
Version: 0.4.29
Summary: Insolver is low-code machine learning library, initially created for the insurance industry.
Home-page: http://insolver.io/
License: MIT
Keywords: insurance,machine learning
Author: Mindset Team
Author-email: request@mind-set.ru
Requires-Python: >=3.8,<3.12
Classifier: Development Status :: 2 - Pre-Alpha
Classifier: Intended Audience :: Financial and Insurance Industry
Classifier: Intended Audience :: Information Technology
Classifier: License :: OSI Approved :: MIT License
Classifier: Operating System :: MacOS :: MacOS X
Classifier: Operating System :: Microsoft :: Windows
Classifier: Operating System :: POSIX :: Linux
Classifier: Programming Language :: Python
Classifier: Programming Language :: Python :: 3
Classifier: Programming Language :: Python :: 3.8
Classifier: Programming Language :: Python :: 3.9
Classifier: Programming Language :: Python :: 3.10
Classifier: Programming Language :: Python :: 3.11
Classifier: Programming Language :: Python :: 3 :: Only
Provides-Extra: all
Provides-Extra: feature-engineering
Provides-Extra: feature-monitoring
Provides-Extra: interpretation
Provides-Extra: report
Provides-Extra: serving
Requires-Dist: Django (>=4.2.15) ; extra == "serving" or extra == "all"
Requires-Dist: Flask (>=2.3.2) ; extra == "serving" or extra == "all"
Requires-Dist: Jinja2 (>=3.1.3) ; extra == "feature-monitoring" or extra == "report" or extra == "serving" or extra == "all"
Requires-Dist: alibi ; extra == "interpretation" or extra == "all"
Requires-Dist: catboost (>=1.0.0)
Requires-Dist: dice-ml ; extra == "interpretation" or extra == "all"
Requires-Dist: dill (>=0.3.4)
Requires-Dist: djangorestframework (>=3.15.2) ; extra == "serving" or extra == "all"
Requires-Dist: fastapi (>=0.109.1) ; extra == "serving" or extra == "all"
Requires-Dist: gunicorn (>=20.0.4) ; extra == "serving" or extra == "all"
Requires-Dist: h2o (>=3.46.0.1)
Requires-Dist: hyperopt (>=0.2.5)
Requires-Dist: lightgbm (>=3.2.0)
Requires-Dist: lime (>=0.2.0.1) ; extra == "interpretation" or extra == "report" or extra == "all"
Requires-Dist: matplotlib (>=3.4.3)
Requires-Dist: numba (>=0.58.0)
Requires-Dist: numpy (>=1.22.0)
Requires-Dist: pandas (>=1.2.0)
Requires-Dist: plotly (>=5.3.1)
Requires-Dist: pydantic (>=2) ; extra == "serving" or extra == "all"
Requires-Dist: scikit-learn (>=1.3.2)
Requires-Dist: scipy (>=1.10.0)
Requires-Dist: seaborn (>=0.12.2)
Requires-Dist: shap (>=0.39.0)
Requires-Dist: statsmodels (>=0.13.1) ; extra == "feature-engineering" or extra == "all"
Requires-Dist: sympy (>=1.9) ; extra == "serving" or extra == "all"
Requires-Dist: uvicorn[standard] (>=0.27) ; extra == "serving" or extra == "all"
Requires-Dist: xgboost (>=1.6.1)
Requires-Dist: ydata-profiling (>=4.7.0) ; extra == "report" or extra == "all"
Project-URL: Bug Tracker, https://github.com/MindSetLib/Insolver/issues
Project-URL: Documentation, https://insolver.readthedocs.io/en/stable/
Project-URL: Repository, https://github.com/MindSetLib/Insolver
